Workbook

Sheet START HERE
A1: NEXTCHAIN.SITE / PHASE 4 ACQUISITION
A3: 15 OCT 2026 • DRAFT • NO AD SPEND OR EXTERNAL POSTS HAVE BEEN EXECUTED
A5: CURRENT DECISIONS
A6: Scope | B6: Phase 4 only: keyword acquisition, Google Search, TikTok creative testing, editorial backlinks.
A7: Priority | B7: High-ticket Search intent first; low-priced subscription via SEO / partners / organic short video.
A8: Connected Google Ads | B8: One KRW account connected; visible live ads currently lead to nextchain.tech, NOT nextchain.site.
A9: TikTok Ads | B9: No TikTok ad account connected as of research time; native connection required.
A10: Go / no go | B10: Do not activate paid campaigns without approved budget, correct serving account and conversion goals.
A11: Google Planner | B11: Vietnam geo ID 2704; Vietnamese language ID 1040; network Google Search.
A12: Keyword volume | B12: 12-month Google Keyword Planner estimate; similar terms can overlap and must not be added.
A13: CPC | B13: Estimated keyword-average CPC; actual auction CPC may differ substantially.
A14: FX (reference) | B14: 1 KRW = 19.272 VND on 2026-10-15; all VND equivalents in Keyword Planner are formulas.
A17: WORKSHEETS
A18: KEYWORD PLANNER | B18: Real search volume and CPC estimates
A19: GOOGLE SEARCH | B19: Campaign, ad group and keyword plan
A20: RSA COPY | B20: Draft Responsive Search Ads copy
A21: NEGATIVES | B21: Negative keyword shortlist
A22: TIKTOK VIDEOS | B22: Short video concepts and hooks
A23: BACKLINKS | B23: Specific placement and editorial prospects
A24: ECONOMICS | B24: CAC and max CPC scenario model
A25: BACKLOG | B25: 14-day execution sequence
A26: SOURCES | B26: Research URLs and caveats

Sheet KEYWORD PLANNER
A1: Cluster | B1: Keyword | C1: Avg searches / month | D1: Avg CPC (KRW) | E1: Ads competition | F1: Competition index | G1: Avg CPC (~VND) | H1: Priority | I1: Target URL | J1: Notes | K1: Source
A2: General | B2: thiết kế website | C2: 40500 | D2: 1714 | E2: LOW | F2: 30 | G2: =IF(D2="","",ROUND(D2*ECONOMICS!$B$5,-3)) -> 33000 | H2: SEO first | I2: https://www.nextchain.site/dich-vu | J2: Broad intent; overlap with "thiết kế web". Avoid broad paid targeting. | K2: Windsor.ai -> Google Ads Keyword Planner (VN geo 2704, VI language 1040, Google Search), fetched 2026-10-15
A3: Core service | B3: dịch vụ thiết kế website | C3: 4400 | D3: 1813 | E3: LOW | F3: 22 | G3: =IF(D3="","",ROUND(D3*ECONOMICS!$B$5,-3)) -> 35000 | H3: P1 Paid | I3: https://www.nextchain.site/dich-vu | J3: High commercial intent; consider bespoke vs subscription offer. | K3: Windsor.ai -> Google Ads Keyword Planner (VN geo 2704, VI language 1040, Google Search), fetched 2026-10-15
A4: Core service | B4: thiết kế website chuyên nghiệp | C4: 2900 | D4: 2746 | E4: LOW | F4: 29 | G4: =IF(D4="","",ROUND(D4*ECONOMICS!$B$5,-3)) -> 53000 | H4: P2 Paid | I4: https://www.nextchain.site/dich-vu/thiet-ke-website-doanh-nghiep | J4: General competitive keyword; screen lead value. | K4: Windsor.ai -> Google Ads Keyword Planner (VN geo 2704, VI language 1040, Google Search), fetched 2026-10-15
A5: Subscription | B5: thiết kế website giá rẻ | C5: 2400 | D5: 3133 | E5: LOW | F5: 12 | G5: =IF(D5="","",ROUND(D5*ECONOMICS!$B$5,-3)) -> 60000 | H5: SEO first | I5: https://www.nextchain.site/bang-gia | J5: Potential CAC > six-month contribution of low-priced plan. | K5: Windsor.ai -> Google Ads Keyword Planner (VN geo 2704, VI language 1040, Google Search), fetched 2026-10-15
A6: Ecommerce | B6: thiết kế website bán hàng | C6: 1600 | D6: 2741 | E6: LOW | F6: 27 | G6: =IF(D6="","",ROUND(D6*ECONOMICS!$B$5,-3)) -> 53000 | H6: P2 Paid | I6: https://www.nextchain.site/dich-vu/thiet-ke-website-ban-hang | J6: Do not promise checkout in 249k plan. | K6: Windsor.ai -> Google Ads Keyword Planner (VN geo 2704, VI language 1040, Google Search), fetched 2026-10-15
A7: Real Estate | B7: thiết kế website bất động sản | C7: 1600 | D7: 1101 | E7: LOW | F7: 18 | G7: =IF(D7="","",ROUND(D7*ECONOMICS!$B$5,-3)) -> 21000 | H7: Test Paid | I7: https://www.nextchain.site/giai-phap/landing-page-bat-dong-san | J7: Need qualify website vs campaign landing page intent. | K7: Windsor.ai -> Google Ads Keyword Planner (VN geo 2704, VI language 1040, Google Search), fetched 2026-10-15
A8: Core service | B8: thiết kế website trọn gói | C8: 1300 | D8: 1843 | E8: LOW | F8: 27 | G8: =IF(D8="","",ROUND(D8*ECONOMICS!$B$5,-3)) -> 36000 | H8: P1 Paid | I8: https://www.nextchain.site/dich-vu | J8: High purchase intent, mixed budget levels. | K8: Windsor.ai -> Google Ads Keyword Planner (VN geo 2704, VI language 1040, Google Search), fetched 2026-10-15
A9: Core service | B9: công ty thiết kế web | C9: 1300 | D9: 3373 | E9: LOW | F9: 10 | G9: =IF(D9="","",ROUND(D9*ECONOMICS!$B$5,-3)) -> 65000 | H9: Test Paid | I9: https://www.nextchain.site/dich-vu | J9: May seek established agency, use real projects. | K9: Windsor.ai -> Google Ads Keyword Planner (VN geo 2704, VI language 1040, Google Search), fetched 2026-10-15
A10: Custom | B10: thiết kế website theo yêu cầu | C10: 1000 | D10: 1738 | E10: LOW | F10: 24 | G10: =IF(D10="","",ROUND(D10*ECONOMICS!$B$5,-3)) -> 33000 | H10: P1 Paid | I10: https://www.nextchain.site/dich-vu/thiet-ke-website-theo-yeu-cau | J10: High-ticket path; use real project proof. | K10: Windsor.ai -> Google Ads Keyword Planner (VN geo 2704, VI language 1040, Google Search), fetched 2026-10-15
A11: Business | B11: thiết kế website doanh nghiệp | C11: 480 | D11: 2981 | E11: MEDIUM | F11: 34 | G11: =IF(D11="","",ROUND(D11*ECONOMICS!$B$5,-3)) -> 57000 | H11: P1 Paid | I11: https://www.nextchain.site/dich-vu/thiet-ke-website-doanh-nghiep | J11: Offer must distinguish monthly vs project. | K11: Windsor.ai -> Google Ads Keyword Planner (VN geo 2704, VI language 1040, Google Search), fetched 2026-10-15
A12: Commercial research | B12: báo giá thiết kế website | C12: 480 | D12: 2402 | E12: LOW | F12: 6 | G12: =IF(D12="","",ROUND(D12*ECONOMICS!$B$5,-3)) -> 46000 | H12: P1 Paid | I12: https://www.nextchain.site/bang-gia | J12: Pricing intent; compare total costs transparently. | K12: Windsor.ai -> Google Ads Keyword Planner (VN geo 2704, VI language 1040, Google Search), fetched 2026-10-15
A13: Subscription | B13: thiết kế website uy tín | C13: 390 | D13: 2346 | E13: LOW | F13: 10 | G13: =IF(D13="","",ROUND(D13*ECONOMICS!$B$5,-3)) -> 45000 | H13: SEO first | I13: https://www.nextchain.site/du-an | J13: Trust-led, show verified portfolio. | K13: Windsor.ai -> Google Ads Keyword Planner (VN geo 2704, VI language 1040, Google Search), fetched 2026-10-15
... A24: Commercial research | B24: bảng giá thiết kế website | C24: 140 | D24: 1209 | E24: LOW | F24: 14 | G24: =IF(D24="","",ROUND(D24*ECONOMICS!$B$5,-3)) -> 23000 | H24: P2 Paid | I24: https://www.nextchain.site/bang-gia | J24: Research and sales-qualified users. | K24: Windsor.ai -> Google Ads Keyword Planner (VN geo 2704, VI language 1040, Google Search), fetched 2026-10-15
A25: Dental | B25: thiết kế website nha khoa | C25: 110 | E25: LOW | F25: 9 | G25: =IF(D25="","",ROUND(D25*ECONOMICS!$B$5,-3)) | H25: SEO first | I25: https://www.nextchain.site/giai-phap/website-nha-khoa | J25: Missing CPC estimate; healthcare content needs trust. | K25: Windsor.ai -> Google Ads Keyword Planner (VN geo 2704, VI language 1040, Google Search), fetched 2026-10-15
A26: Real Estate | B26: landing page bất động sản | C26: 110 | D26: 657 | E26: HIGH | F26: 93 | G26: =IF(D26="","",ROUND(D26*ECONOMICS!$B$5,-3)) -> 13000 | H26: Test Paid | I26: https://www.nextchain.site/giai-phap/landing-page-bat-dong-san | J26: Correct landing-page intent. | K26: Windsor.ai -> Google Ads Keyword Planner (VN geo 2704, VI language 1040, Google Search), fetched 2026-10-15
A27: Commercial research | B27: chi phí thiết kế website | C27: 110 | D27: 1566 | E27: LOW | F27: 22 | G27: =IF(D27="","",ROUND(D27*ECONOMICS!$B$5,-3)) -> 30000 | H27: SEO first | I27: https://www.nextchain.site/blog/chi-phi-thiet-ke-landing-page | J27: Generic term may need separate comparison article. | K27: Windsor.ai -> Google Ads Keyword Planner (VN geo 2704, VI language 1040, Google Search), fetched 2026-10-15
A28: Custom | B28: thiết kế website giáo dục | C28: 70 | D28: 1503 | E28: LOW | F28: 32 | G28: =IF(D28="","",ROUND(D28*ECONOMICS!$B$5,-3)) -> 29000 | H28: SEO first | I28: https://www.nextchain.site/giai-phap/landing-page-khoa-hoc | J28: Website for education vs landing page for courses. | K28: Windsor.ai -> Google Ads Keyword Planner (VN geo 2704, VI language 1040, Google Search), fetched 2026-10-15
A29: Hotel | B29: thiết kế website khách sạn | C29: 70 | D29: 2801 | E29: MEDIUM | F29: 39 | G29: =IF(D29="","",ROUND(D29*ECONOMICS!$B$5,-3)) -> 54000 | H29: Test Paid | I29: https://www.nextchain.site/giai-phap/website-homestay | J29: Hospitality focus; no automated inventory unless custom. | K29: Windsor.ai -> Google Ads Keyword Planner (VN geo 2704, VI language 1040, Google Search), fetched 2026-10-15
A30: Beauty | B30: thiết kế website spa | C30: 50 | D30: 4127 | E30: LOW | F30: 31 | G30: =IF(D30="","",ROUND(D30*ECONOMICS!$B$5,-3)) -> 80000 | H30: SEO first | I30: https://www.nextchain.site/giai-phap/website-spa | J30: High estimated CPC; prefer organic and partners. | K30: Windsor.ai -> Google Ads Keyword Planner (VN geo 2704, VI language 1040, Google Search), fetched 2026-10-15
A31: Training | B31: landing page khóa học | C31: 40 | D31: 99 | E31: MEDIUM | F31: 44 | G31: =IF(D31="","",ROUND(D31*ECONOMICS!$B$5,-3)) -> 2000 | H31: Test Paid | I31: https://www.nextchain.site/giai-phap/landing-page-khoa-hoc | J31: Small volume, intent check for template-seekers. | K31: Windsor.ai -> Google Ads Keyword Planner (VN geo 2704, VI language 1040, Google Search), fetched 2026-10-15
A32: Cafe | B32: thiết kế website quán cà phê | C32: 20 | E32: MEDIUM | F32: 39 | G32: =IF(D32="","",ROUND(D32*ECONOMICS!$B$5,-3)) | H32: SEO first | I32: https://www.nextchain.site/giai-phap/website-quan-ca-phe | J32: Tiny demand; offer may do better via direct outreach. | K32: Windsor.ai -> Google Ads Keyword Planner (VN geo 2704, VI language 1040, Google Search), fetched 2026-10-15
A33: Subscriptions | B33: dịch vụ website trọn gói | C33: 20 | D33: 3345 | E33: LOW | F33: 23 | G33: =IF(D33="","",ROUND(D33*ECONOMICS!$B$5,-3)) -> 64000 | H33: SEO first | I33: https://www.nextchain.site/dich-vu | J33: Volume small; campaign not standalone. | K33: Windsor.ai -> Google Ads Keyword Planner (VN geo 2704, VI language 1040, Google Search), fetched 2026-10-15
A34: Discount intent | B34: thiết kế website miễn phí | C34: 260 | D34: 832 | E34: MEDIUM | F34: 51 | G34: =IF(D34="","",ROUND(D34*ECONOMICS!$B$5,-3)) -> 16000 | H34: Exclude paid | I34: https://www.nextchain.site/dich-vu | J34: Not interested in paid service. | K34: Windsor.ai -> Google Ads Keyword Planner (VN geo 2704, VI language 1040, Google Search), fetched 2026-10-15
A35: Informational | B35: landing page mẫu | C35: 480 | D35: 451 | E35: HIGH | F35: 100 | G35: =IF(D35="","",ROUND(D35*ECONOMICS!$B$5,-3)) -> 9000 | H35: SEO first | I35: https://www.nextchain.site/mau-website | J35: Examples, not purchase; do not buy clicks initially. | K35: Windsor.ai -> Google Ads Keyword Planner (VN geo 2704, VI language 1040, Google Search), fetched 2026-10-15

Sheet GOOGLE SEARCH
A1: Campaign | B1: Ad Group | C1: Keyword | D1: Final URL | E1: Status | F1: Offer tier | G1: Notes
A2: NCsite_VN_Search_Core | B2: Agency_Hire | C2: [dịch vụ thiết kế website] | D2: https://www.nextchain.site/dich-vu | E2: DRAFT - DO NOT POST | F2: B2B/custom | G2: Exact/phrase only; do not activate until account, goal and budget are approved.
A3: NCsite_VN_Search_Core | B3: Agency_Hire | C3: "dịch vụ thiết kế website trọn gói" | D3: https://www.nextchain.site/dich-vu | E3: DRAFT - DO NOT POST | F3: B2B/custom | G3: Exact/phrase only; do not activate until account, goal and budget are approved.
A4: NCsite_VN_Search_Core | B4: Agency_Hire | C4: "thiết kế website trọn gói" | D4: https://www.nextchain.site/dich-vu | E4: DRAFT - DO NOT POST | F4: B2B/custom | G4: Exact/phrase only; do not activate until account, goal and budget are approved.
A5: NCsite_VN_Search_Core | B5: Agency_Hire | C5: [thiết kế website chuyên nghiệp] | D5: https://www.nextchain.site/dich-vu | E5: DRAFT - DO NOT POST | F5: B2B/custom | G5: Exact/phrase only; do not activate until account, goal and budget are approved.
A6: NCsite_VN_Search_Core | B6: Business_Web | C6: [thiết kế website doanh nghiệp] | D6: https://www.nextchain.site/dich-vu/thiet-ke-website-doanh-nghiep | E6: DRAFT - DO NOT POST | F6: Project | G6: Exact/phrase only; do not activate until account, goal and budget are approved.
A7: NCsite_VN_Search_Core | B7: Business_Web | C7: "thiết kế website công ty" | D7: https://www.nextchain.site/dich-vu/thiet-ke-website-doanh-nghiep | E7: DRAFT - DO NOT POST | F7: Project | G7: Exact/phrase only; do not activate until account, goal and budget are approved.
A8: NCsite_VN_Search_Core | B8: Business_Web | C8: "thiết kế website cho doanh nghiệp" | D8: https://www.nextchain.site/dich-vu/thiet-ke-website-doanh-nghiep | E8: DRAFT - DO NOT POST | F8: Project | G8: Exact/phrase only; do not activate until account, goal and budget are approved.
A9: NCsite_VN_Search_Core | B9: Custom_Web | C9: [thiết kế website theo yêu cầu] | D9: https://www.nextchain.site/dich-vu/thiet-ke-website-theo-yeu-cau | E9: DRAFT - DO NOT POST | F9: Project | G9: Exact/phrase only; do not activate until account, goal and budget are approved.
A10: NCsite_VN_Search_Core | B10: Custom_Web | C10: "thiết kế website theo yêu cầu" | D10: https://www.nextchain.site/dich-vu/thiet-ke-website-theo-yeu-cau | E10: DRAFT - DO NOT POST | F10: Project | G10: Exact/phrase only; do not activate until account, goal and budget are approved.
A11: NCsite_VN_Search_Core | B11: Landing_Page | C11: [dịch vụ thiết kế landing page] | D11: https://www.nextchain.site/dich-vu/thiet-ke-landing-page | E11: DRAFT - DO NOT POST | F11: Mixed | G11: Exact/phrase only; do not activate until account, goal and budget are approved.
A12: NCsite_VN_Search_Core | B12: Landing_Page | C12: "thiết kế landing page" | D12: https://www.nextchain.site/dich-vu/thiet-ke-landing-page | E12: DRAFT - DO NOT POST | F12: Mixed | G12: Exact/phrase only; do not activate until account, goal and budget are approved.
... A25: NCsite_VN_Search_Price_Test | B25: Website_Pricing | C25: "thiết kế website giá rẻ" | D25: https://www.nextchain.site/bang-gia | E25: DRAFT - DO NOT POST | F25: Monthly | G25: Exact/phrase only; do not activate until account, goal and budget are approved.

Sheet RSA COPY
A1: Campaign | B1: Ad Group | C1: Final URL | D1: Headline 1 | E1: Headline 2 | F1: Headline 3 | G1: Headline 4 | H1: Headline 5 | I1: Headline 6 | J1: Headline 7 | K1: Headline 8 | L1: Headline 9 | M1: Headline 10 | N1: Description 1 | O1: Description 2 | P1: Description 3 | Q1: Description 4 | R1: Status
A2: NCsite_VN_Search_Core | B2: Agency_Hire | C2: https://www.nextchain.site/dich-vu | D2: Thiết Kế Website Trọn Gói | E2: Nextchain Thiết Kế Website | F2: Xem Dự Án Nextchain Đã Làm | G2: Website Cho Doanh Nghiệp | H2: Có Mẫu Website Tham Khảo | I2: Đội Ngũ Thiết Kế Và Vận Hành | J2: Giao Diện Tốt Trên Mobile | K2: Tư Vấn Gói Website Phù Hợp | L2: Xem Bảng Giá Minh Bạch | M2: Từ Ý Tưởng Đến Website | N2: Nextchain thiết kế và vận hành website theo nhu cầu. Xem dự án thật và các gói dịch vụ. | O2: Website doanh nghiệp, landing page hoặc dự án riêng. Tham khảo mẫu và nhận tư vấn. | P2: Chọn loại website phù hợp ngành nghề, quy mô và ngân sách trước khi triển khai. | Q2: Xem quy trình Nextchain thực hiện, bảng giá và ví dụ các dự án đã bàn giao. | R2: DRAFT
A3: NCsite_VN_Search_Core | B3: Business_Web | C3: https://www.nextchain.site/dich-vu/thiet-ke-website-doanh-nghiep | D3: Thiết Kế Web Doanh Nghiệp | E3: Website Thể Hiện Năng Lực | F3: Xem Portfolio Nextchain | G3: Thiết Kế Tốt Trên Mobile | H3: Tư Vấn Website Theo Nhu Cầu | I3: Dự Án Có Quy Trình Rõ Ràng | J3: Website Cho Công Ty | K3: Xem Giá Và Phạm Vi Công Việc | L3: Xem Dự Án Thực Tế | M3: Liên Hệ Đội Ngũ Nextchain | N3: Website doanh nghiệp có cấu trúc rõ ràng, dễ giới thiệu dịch vụ và nhận yêu cầu. | O3: Xem dự án thực tế do Nextchain phát triển, đối chiếu chức năng trước khi trao đổi. | P3: Tư vấn giải pháp web phù hợp với quy mô doanh nghiệp và nhu cầu kinh doanh. | Q3: Dịch vụ website doanh nghiệp theo phạm vi dự án, có thông tin giá và quy trình. | R3: DRAFT
A4: NCsite_VN_Search_Core | B4: Custom_Web | C4: https://www.nextchain.site/dich-vu/thiet-ke-website-theo-yeu-cau | D4: Thiết Kế Website Theo Yêu Cầu | E4: Website Theo Quy Trình Riêng | F4: Nextchain Phát Triển Website | G4: Giải Pháp Web Cho Doanh Nghiệp | H4: Xem 7 Dự Án Thực Tế | I4: Tư Vấn Chức Năng Cần Thiết | J4: Từ Yêu Cầu Đến Bàn Giao | K4: Đội Ngũ Web Theo Dự Án | L4: Xem Năng Lực Nextchain | M4: Nhận Tư Vấn Dự Án Web | N4: Thiết kế website theo quy trình kinh doanh riêng, phù hợp yêu cầu và ngân sách. | O4: Tham khảo những dự án Nextchain đã phát triển trước khi bắt đầu dự án mới. | P4: Tư vấn chức năng, phạm vi phát triển và cách triển khai cho website theo yêu cầu. | Q4: Website theo yêu cầu dành cho doanh nghiệp có nghiệp vụ hoặc tích hợp riêng. | R4: DRAFT
A5: NCsite_VN_Search_Core | B5: Landing_Page | C5: https://www.nextchain.site/dich-vu/thiet-ke-landing-page | D5: Thiết Kế Landing Page Trọn Gói | E5: Xem Mẫu Landing Page | F5: Từ 249.000đ Mỗi Tháng | G5: Không Phí Khởi Tạo | H5: Nextchain Làm Bạn Duyệt | I5: Landing Page Cho Kinh Doanh | J5: Có Nút Gọi Và Form Liên Hệ | K5: Xem Quy Trình Rõ Ràng | L5: Giao Diện Tốt Trên Mobile | M5: Tư Vấn Gói Phù Hợp | N5: Landing page giới thiệu dịch vụ, có form nhận liên hệ, thiết kế và vận hành theo tháng. | O5: Gói khởi điểm từ 249.000đ/tháng. Xem rõ phạm vi từng gói và điều khoản trước khi chọn. | P5: Nextchain viết nội dung, thiết kế, xuất bản và hỗ trợ cập nhật theo phạm vi gói. | Q5: Xem giao diện demo và bảng giá website theo tháng dành cho cơ sở kinh doanh nhỏ. | R5: DRAFT
A6: NCsite_VN_Search_Vertical_Test | B6: Real_Estate | C6: https://www.nextchain.site/giai-phap/landing-page-bat-dong-san | D6: Landing Page Bất Động Sản | E6: Trang Giới Thiệu Dự Án BĐS | F6: Form Nhận Tư Vấn Khách Hàng | G6: Xem Mẫu Landing Page BĐS | H6: Giao Diện Dự Án Rõ Ràng | I6: Có Mặt Bằng Và Tiện Ích | J6: Thiết Kế Theo Nội Dung Dự Án | K6: Tư Vấn Phạm Vi Và Chi Phí | L6: Xem Giải Pháp Nextchain | M6: Có Demo Để Tham Khảo | N6: Landing page bất động sản có vị trí, mặt bằng, tiện ích và form yêu cầu tư vấn. | O6: Nội dung dự án do chủ sở hữu xác nhận. Xem mẫu bố cục và các gói phù hợp. | P6: Website giới thiệu dự án trên điện thoại, khách tìm thông tin và gửi yêu cầu rõ ràng. | Q6: Trao đổi quy mô, thông tin pháp lý và phạm vi triển khai với Nextchain. | R6: DRAFT
A7: NCsite_VN_Search_Vertical_Test | B7: Restaurant | C7: https://www.nextchain.site/giai-phap/website-quan-ca-phe | D7: Website Nhà Hàng Và Quán Cafe | E7: Xem Mẫu Website F&B | F7: Menu Dễ Xem Trên Điện Thoại | G7: Khách Dễ Tìm Đường Đến Quán | H7: Thiết Kế Website Cho Nhà Hàng | I7: Bảng Giá Website Minh Bạch | J7: Nextchain Làm Bạn Duyệt | K7: Có Nút Gọi Và Liên Hệ | L7: Xem Website Mẫu F&B | M7: Tư Vấn Website Theo Quán | N7: Website cho quán ăn, cà phê và nhà hàng: giới thiệu thực đơn, hình ảnh và địa chỉ. | O7: Mẫu website F&B hiển thị tốt trên mobile, có nút gọi và chỉ đường cho khách. | P7: Nextchain thiết kế và cập nhật theo gói. Xem mẫu, bảng giá và cách triển khai. | Q7: Tư vấn website giới thiệu cho cơ sở ăn uống, không tự nhận là phần mềm POS. | R7: DRAFT

Sheet NEGATIVES
A1: Scope | B1: Negative keyword | C1: Exclusion reason
A2: All Search | B2: tuyển dụng | C2: Intent việc làm
A3: All Search | B3: việc làm | C3: Intent tuyển dụng
A4: All Search | B4: internship | C4: Học nghề
A5: All Search | B5: thực tập | C5: Học nghề
A6: All Search | B6: đồ án | C6: Bài tập sinh viên
A7: All Search | B7: bài tập | C7: Học tập
A8: All Search | B8: source code | C8: Tìm mã nguồn
A9: All Search | B9: mã nguồn miễn phí | C9: Tìm mã nguồn
A10: All Search | B10: github | C10: Tải code
A11: All Search | B11: tải về miễn phí | C11: Tải tài nguyên
A12: All Search | B12: template miễn phí | C12: Free assets
... A29: Custom_Web | B29: học lập trình web | C29: DIY intent

Sheet TIKTOK VIDEOS
A1: ID | B1: Target | C1: Video hook | D1: Scene / storyboard | E1: On-screen truth | F1: CTA | G1: Objective | H1: Landing path | I1: Hypothesis / variant
A2: TT01 | B2: SMB/F&B | C2: Chủ quán có fanpage rồi, có cần website không? | D2: 0–3s: quay fanpage; 3–9s: mở demo quán cafe; 9–17s: menu/bản đồ/nút gọi; 17–22s: gói giá và CTA | E2: Fanpage để trò chuyện. Website để tra thông tin rõ hơn. | F2: Xem demo F&B | G2: Lead Gen / Organic | H2: /giai-phap/website-quan-ca-phe | I2: Pain-led vs visual proof
A3: TT02 | B3: Small business | C3: 249.000đ/tháng thì website trông như thế nào? | D3: 0–3s: hiện giá; 3–15s: screen record demo mobile; 15–21s: phạm vi một landing page; 21–26s: chỉ rõ nâng cấp | E3: Từ 249k/tháng, gói Khởi đầu chỉ gồm 1 landing page. | F3: Xem bảng giá | G3: Lead Gen / Organic | H3: /bang-gia | I3: Price-led + honesty
A4: TT03 | B4: B2B / Custom | C4: 7 dự án thật cho thấy Nextchain làm được gì | D4: 0–4s: intro; 4–20s: flash 3 case studies có thật; 20–28s: case project vs thuê bao; 28–32s: CTA | E4: Website theo yêu cầu khác gói landing page theo tháng. | F4: Xem dự án | G4: Website Conversions | H4: /du-an | I4: Proof-led vs pitch-led
A5: TT04 | B5: Homestay | C5: Khách hỏi phòng trên Zalo cả ngày? | D5: 0–3s: inbox hỏi phòng; 3–14s: demo homestay, giá, gallery; 14–23s: form yêu cầu, chủ nhà xác nhận | E5: Website trưng bày phòng + form hỏi phòng, không hứa booking engine. | F5: Xem mẫu Homestay | G5: Lead Gen / Organic | H5: /giai-phap/website-homestay | I5: Workflow demo
A6: TT05 | B6: Beauty / Nail | C6: Bảng giá spa nằm tận đâu trong Fanpage? | D6: 0–3s: scroll fanpage; 3–13s: demo dịch vụ/bảng giá; 13–20s: CTA | E6: Để bảng giá và dịch vụ trong một link dễ gửi. | F6: Xem mẫu Spa | G6: Lead Gen / Organic | H6: /giai-phap/website-spa | I6: Discovery pain
A7: TT06 | B7: Salon | C7: Khách xem kiểu tóc và giá ở đâu? | D7: 0–3s: câu hỏi; 3–12s: gallery salon; 12–20s: giá, nút hẹn; 20–25s: CTA | E7: Portfolio + bảng giá + nút liên hệ trong một website. | F7: Xem mẫu Salon | G7: Lead Gen / Organic | H7: /giai-phap/website-salon | I7: Visual demo
A8: TT07 | B8: Retail | C8: Website bán hàng 249k có giỏ hàng không? | D8: 0–3s: hỏi đáp; 3–15s: phân biệt catalog/form và checkout; 15–24s: đưa ví dụ theo gói | E8: Nói rõ có gì trong gói, không hứa giỏ hàng cho gói Khởi đầu. | F8: Xem phạm vi gói | G8: Organic | H8: /bang-gia | I8: Trust/transparency
A9: TT08 | B9: All industries | C9: Tự làm website hay thuê đơn vị làm trọn gói? | D9: 0–4s: so sánh; 4–18s: thời gian tự nhập/chỉnh sửa vs dùng dịch vụ; 18–28s: CTA | E9: Không cần tự quản trị kỹ thuật nếu dùng dịch vụ phù hợp. | F9: Xem so sánh | G9: Lead Gen / Organic | H9: /blog/lam-website-theo-goi-thang-hay-tra-mot-lan | I9: Educational comparison

Sheet BACKLINKS
A1: Source | B1: Source URL | C1: Type | D1: Target path | E1: Submission route | F1: Priority | G1: Editorial / policy note
A2: Trang Vàng Việt Nam | B2: https://trangvangvietnam.com/dang-ky | C2: Business directory | D2: Homepage | E2: Direct profile | F2: Do immediately | G2: Business listing with verifiable company data
A3: LinkedIn Company Page | B3: https://www.linkedin.com/ | C3: Brand profile | D3: Homepage | E3: Direct profile | F3: Do immediately | G3: Company page, source of trust, no assumed dofollow
A4: Behance | B4: https://www.behance.net/ | C4: Portfolio | D4: /mau-website | E4: Self-publish project | F4: Do immediately | G4: 5-7 real creative case studies or demos
A5: KenhRao | B5: https://kenhrao.com/rao-vat/dich-vu-doanh-nghiep.52/ | C5: Classified/forum | D5: /dich-vu | E5: Post in allowed section | F5: Pilot | G5: One truthful service listing only
A6: VietDesigner - Quang cao | B6: https://forum.vietdesigner.net/forums/quang-cao/ | C6: Design forum | D6: /mau-website | E6: Post following rules | F6: Pilot | G6: Share real design work; no spam
A7: Lam Cha Me | B7: https://forum.lamchame.com/forum/ | C7: SMB forum | D7: /dich-vu | E7: Check suitable area | F7: Pilot | G7: Manual review of category rules
A8: OCD.vn | B8: https://ocd.vn/write-for-us-share-your-expertise-on-business-and-technology-in-vietnam/ | C8: Guest editorial | D8: /blog | E8: Pitch | F8: High priority | G8: Original 800+ words; pitch gp@ocd.vn
A9: Brands Vietnam | B9: https://www.brandsvietnam.com/community/ | C9: Editorial/community | D9: /blog | E9: Submit approved research | F9: High priority | G9: Needs real dataset or unique specialist content
A10: TechBehemoths | B10: https://techbehemoths.com/companies/get-listed | C10: Agency directory | D10: Homepage | E10: Company application | F10: After profile ready | G10: Web design credibility vs Vietnamese local leads
A11: GoodFirms | B11: https://www.goodfirms.co/get-listed | C11: Agency directory | D11: Homepage | E11: Company application | F11: After proof ready | G11: Free profile; review process
A12: Clutch | B12: https://clutch.co/get-listed | C12: Agency directory | D12: Homepage | E12: Company application | F12: Low priority | G12: Free profile does not guarantee directory website link
A13: Cộng Đồng Spa | B13: https://congdongspa.com/gioi-thieu/ | C13: Industry partners | D13: /giai-phap/website-spa | E13: Partnership outreach | F13: Selective | G13: Pitch useful asset not a paid dofollow

Sheet ECONOMICS
A1: UNIT ECONOMICS / EDIT BLUE INPUTS
A5: FX: VND / KRW | B5: 19.272 | C5: Market rate 2026-10-15; currency source result
A6: Subscription term (months) | B6: 6 | C6: Assumption based on six-month commercial commitment; verify offer.
A7: Gross margin assumption | B7: 0.6 | C7: Illustrative; replace with actual delivery/maintenance cost margin.
A8: Maximum CAC / gross contribution | B8: 0.3 | C8: Marketing risk assumption; not industry benchmark.
A9: Form conversion from paid click | B9: 0.06 | C9: Scenario only; replace with tested valid form rate.
A10: Qualified / submitted lead | B10: 0.6 | C10: Scenario only, not Nextchain historical data.
A11: Closed / qualified lead | B11: 0.25 | C11: Scenario only; replace with CRM close rate.
A12: Suggested Google Search pilot budget (VND) | B12: 7000000 | C12: UNAPPROVED DRAFT, does not spend money.
A13: Suggested TikTok paid pilot budget (VND) | B13: 4000000 | C13: UNAPPROVED DRAFT; must meet TikTok account minimum budgets.
A16: Plan | B16: Monthly revenue VND | C16: 6-month revenue VND | D16: Gross contribution VND | E16: CAC cap VND | F16: Max CPC break-even policy VND | G16: Planner benchmark CPC VND | H16: Interpretation
A17: Start | B17: 249000 | C17: =B17*$B$6 -> 1494000 | D17: =C17*$B$7 -> 896400 | E17: =D17*$B$8 -> 268920 | F17: =E17*$B$9*$B$10*$B$11 -> 2420.28 | G17: =ROUND(1813*$B$5,-3) -> 35000 | H17: =IF(F17>=G17,"Test economics","Organic/partners first") -> Organic/partners first
A18: Growth | B18: 790000 | C18: =B18*$B$6 -> 4740000 | D18: =C18*$B$7 -> 2844000 | E18: =D18*$B$8 -> 853200 | F18: =E18*$B$9*$B$10*$B$11 -> 7678.8 | G18: =ROUND(1813*$B$5,-3) -> 35000 | H18: =IF(F18>=G18,"Test economics","Organic/partners first") -> Organic/partners first
A19: Pro | B19: 1490000 | C19: =B19*$B$6 -> 8940000 | D19: =C19*$B$7 -> 5364000 | E19: =D19*$B$8 -> 1609200 | F19: =E19*$B$9*$B$10*$B$11 -> 14482.8 | G19: =ROUND(1813*$B$5,-3) -> 35000 | H19: =IF(F19>=G19,"Test economics","Organic/partners first") -> Organic/partners first
A22: Interpretation | B22: The basic 249k/month plan is unlikely to sustain broad Google Search acquisition at Planner CPC unless close/retention/margin improve. The model is illustrative and NOT a sales forecast.
A24: TikTok minimums | B24: TikTok documentation: if campaign-level daily budget is set, must exceed US$50; ad group daily >US$20. Without campaign budget, ad-group minimum still applies. Validate account-specific local limits.

Sheet BACKLOG
A1: Window | B1: ID | C1: Workstream | D1: Action | E1: Owner | F1: State | G1: Acceptance
A2: D1 | B2: ACQ-001 | C2: Account mapping | D2: Confirm Google Ads serving account for nextchain.site; no mixing with tech account | E2: CMO | F2: Blocked | G2: Account + billing currency + goals signed off
A3: D1 | B3: ACQ-002 | C3: TikTok connector | D3: Link TikTok Ads account in Windsor.ai or TikTok Ads Manager | E3: CMO | F3: Blocked | G3: Connected account id, pixel/account status reviewed
A4: D1 | B4: ACQ-003 | C4: Budget approval | D4: Choose VN budget and limits for paid pilots | E4: Owner | F4: Blocked | G4: Explicit amount and duration approved
A5: D1-2 | B5: SEO-101 | C5: Keyword shortlist | D5: Review Planner numbers and select intent clusters | E5: SEO | F5: Ready | G5: Landing page per ad group
A6: D2 | B6: ADS-101 | C6: Google Ads structure | D6: Prepare 1 core Search campaign + 3-4 ad groups | E6: PPC | F6: Draft | G6: Geo VN, offers matched, campaign-specific goal
A7: D2 | B7: ADS-102 | C7: Conversion and attribution QA | D7: Verify ads goal, GCLID, lead-qualified tracking | E7: PPC | F7: Draft | G7: Test lead attributed; not conflated with tech
A8: D3 | B8: ADS-103 | C8: Ad copy | D8: Import RSA drafts after human copy review | E8: Copywriter | F8: Draft | G8: Headline <=30, description <=90
A9: D3 | B9: ADS-104 | C9: Negative keywords | D9: Seed shared negatives and review search terms | E9: PPC | F9: Draft | G9: No DIY/free/junior intent leak
A10: D3-4 | B10: TT-101 | C10: Organic video sprint | D10: Produce 4 actual screen-recorded demos | E10: Creative | F10: Draft | G10: 9:16; business-specific CTA; no fake proof
A11: D4 | B11: TT-102 | C11: TikTok lead events | D11: Pixel if website form; native lead CRM sync if instant form | E11: Analytics | F11: Draft | G11: Lead captured; qualifies as real contact
A12: D4-5 | B12: BL-101 | C12: Foundational profiles | D12: Trang Vang LinkedIn Behance | E12: Growth | F12: Draft | G12: At least 3 live public placement URLs
... A18: D14 | B18: ACQ-100 | C18: Channel gate | D18: Decide scale/kill based on qualified SQL and economics | E18: CMO | F18: Pending | G18: Channel decision and next-month budget

Sheet SOURCES
A1: Source | B1: URL | C1: Use / qualification
A2: Nextchain site project/pricing | B2: https://github.com/nextchaindev/nextjs-landing-page | C2: Read code and offer in previous audit, including pricing and route slugs
A3: Keyword Planner authenticated source | B3: https://support.google.com/google-ads/answer/7337243 | C3: Windsor.ai Google Ads Keyword Planner; Vietnam 2704; Vietnamese 1040; fetched 2026-10-15; KRW currency
A4: Google language criterion | B4: https://developers.google.com/google-ads/api/data/codes-formats | C4: Vietnamese language ID 1040
A5: Google Ads geo targets | B5: https://developers.google.com/google-ads/api/data/geotargets | C5: Geo targets use criterion IDs; Vietnam 2704
A6: Google Ads keyword matching | B6: https://support.google.com/google-ads/answer/7478529 | C6: Exact and phrase match semantics
A7: Google Ads negative keywords | B7: https://support.google.com/google-ads/answer/2453972 | C7: Negative keyword strategy
A8: Google Ads Editor CSV | B8: https://support.google.com/google-ads/editor/answer/56368 | C8: Bulk import format; review before posting
A9: Google Ads primary conversion | B9: https://support.google.com/google-ads/answer/11461796 | C9: Primary/Secondary and campaign-specific bidding
A10: TikTok budget | B10: https://ads.tiktok.com/help/article/budget?lang=vi | C10: Campaign >US$50 and ad group >US$20 if daily budgets used
A11: TikTok Leads | B11: https://ads.tiktok.com/resources/help/article/lead-generation-objective | C11: Lead gen: website or instant form
A12: TikTok CRM signals | B12: https://ads.tiktok.com/help/article/about-signal-optimization-for-lead-generation-campaigns?lang=en | C12: Qualified Lead CRM postback
... A17: Currency conversion | B17: https://www.xe.com/currencyconverter/ | C17: Actual time-specific FX was retrieved via the currency source at 2026-10-15T07:30Z
